dictwrapper/__init__.py
dictwrapper/nested.py
dictwrapper/wrapper.py
dictwrapper-1.6.dist-info/METADATA
dictwrapper-1.6.dist-info/WHEEL
dictwrapper-1.6.dist-info/top_level.txt
dictwrapper-1.6.dist-info/RECORD
