Metadata-Version: 2.1
Name: dictwrapper
Version: 1.6
Summary: Basic Dictionary Wrapper
Home-page: UNKNOWN
Author: Nicolas Deutschmann
Author-email: nicolas.deutschmann@gmail.com
License: MIT
Platform: UNKNOWN
Requires-Dist: pyyaml (>=6.0)
Requires-Dist: pandas (>=1.1)
